README.md
setup.py
yt_lib/__init__.py
yt_lib/client.py
yt_lib/common.py
yt_lib/constants.py
yt_lib/exceptions.py
yt_lib/states.py
yt_lib/utils.py
yt_lib.egg-info/PKG-INFO
yt_lib.egg-info/SOURCES.txt
yt_lib.egg-info/dependency_links.txt
yt_lib.egg-info/top_level.txt