Metadata-Version: 2.1
Name: yt-lib
Version: 0.0.1
Summary: Young YouTube library
Home-page: https://github.com/hairygeek/yt_lib
Author: hairygeek
Author-email: hairygeek@yandex.com
License: UNKNOWN
Platform: UNKNOWN
Classifier: Programming Language :: Python :: 3.7
Classifier: License :: OSI Approved :: MIT License
Classifier: Operating System :: OS Independent
